Metadata-Version: 1.0
Name: distributions-skjohn24
Version: 0.1
Summary: Gaussian and Binomial distributions
Home-page: UNKNOWN
Author: skjohn
Author-email: UNKNOWN
License: UNKNOWN
Platform: UNKNOWN
